arielbot/__init__.py
arielbot/bot.py
arielbot/plugins/Core/__init__.py
arielbot/plugins/Core/ariel_bili.py
arielbot/plugins/Core/ariel_cmd.py
arielbot/plugins/Core/ariel_cookie.py
arielbot/plugins/Core/ariel_database.py
arielbot/plugins/Core/ariel_push.py
arielbot/plugins/Core/ariel_rule.py
arielbot/plugins/Core/ariel_tools.py
arielbot-0.4.9.dist-info/METADATA
arielbot-0.4.9.dist-info/WHEEL
arielbot-0.4.9.dist-info/entry_points.txt
arielbot-0.4.9.dist-info/RECORD
