Metadata-Version: 2.3
Name: arielBot
Version: 0.4.9
Summary: 
License: MIT
Author: Polyisoprene
Author-email: lzxder@outlook.com
Requires-Python: >=3.10,<4.0
Classifier: License :: OSI Approved :: MIT License
Classifier: Programming Language :: Python :: 3
Classifier: Programming Language :: Python :: 3.10
Classifier: Programming Language :: Python :: 3.11
Classifier: Programming Language :: Python :: 3.12
Classifier: Programming Language :: Python :: 3.13
Requires-Dist: aiosqlite (>=0.21.0,<0.22.0)
Requires-Dist: click (>=8.1.7,<9.0.0)
Requires-Dist: dynrender-skia (>=0.2.9,<0.3.0)
Requires-Dist: fastapi (>=0.111.0,<0.112.0)
Requires-Dist: nonebot-adapter-onebot (>=2.4.3,<3.0.0)
Requires-Dist: nonebot-plugin-apscheduler (>=0.5.0,<0.6.0)
Requires-Dist: nonebot2 (>=2.3.1,<3.0.0)
Requires-Dist: pycryptodome (>=3.21.0,<4.0.0)
Requires-Dist: pypng (>=0.20220715.0,<0.20220716.0)
Requires-Dist: qrcode (>=8.0,<9.0)
